README.md
setup.py
Shenma/__init__.py
Shenma/sound.py
Shenma/speech.py
Shenma/translate.py
Shenma.egg-info/PKG-INFO
Shenma.egg-info/SOURCES.txt
Shenma.egg-info/dependency_links.txt
Shenma.egg-info/requires.txt
Shenma.egg-info/top_level.txt