Metadata-Version: 2.1
Name: Shenma
Version: 0.1.7
Summary: A custom library for teaching, maintained by CherryXuan
Home-page: https://gitee.com/cherryxuan/SpeechRecognition
Author: CherryXuan
Author-email: shenzexuan1994@foxmail.com
Maintainer: CherryXuan
Maintainer-email: shenzexuan1994@foxmail.com
License: MIT Licence
Platform: all
Classifier: Development Status :: 4 - Beta
Classifier: Operating System :: OS Independent
Classifier: Intended Audience :: Developers
Classifier: License :: OSI Approved :: MIT License
Classifier: Programming Language :: Python :: 3.6
Classifier: Topic :: Software Development :: Libraries
